easyocr/__init__.py
easyocr/cli.py
easyocr/config.py
easyocr/craft.py
easyocr/craft_utils.py
easyocr/detection.py
easyocr/easyocr.py
easyocr/example.py
easyocr/imgproc.py
easyocr/recognition.py
easyocr/utils.py
easyocr/character/ab_char.txt
easyocr/character/abq_char.txt
easyocr/character/ady_char.txt
easyocr/character/af_char.txt
easyocr/character/ang_char.txt
easyocr/character/ar_char.txt
easyocr/character/as_char.txt
easyocr/character/ava_char.txt
easyocr/character/az_char.txt
easyocr/character/be_char.txt
easyocr/character/bg_char.txt
easyocr/character/bh_char.txt
easyocr/character/bho_char.txt
easyocr/character/bn_char.txt
easyocr/character/bs_char.txt
easyocr/character/ch_pin_char.txt
easyocr/character/ch_sim_char.txt
easyocr/character/ch_tra_char.txt
easyocr/character/che_char.txt
easyocr/character/cs_char.txt
easyocr/character/cy_char.txt
easyocr/character/da_char.txt
easyocr/character/dar_char.txt
easyocr/character/de_char.txt
easyocr/character/en_char.txt
easyocr/character/es_char.txt
easyocr/character/et_char.txt
easyocr/character/fa_char.txt
easyocr/character/fr_char.txt
easyocr/character/ga_char.txt
easyocr/character/gom_char.txt
easyocr/character/he_char.txt
easyocr/character/hi_char.txt
easyocr/character/hr_char.txt
easyocr/character/hu_char.txt
easyocr/character/id_char.txt
easyocr/character/inh_char.txt
easyocr/character/is_char.txt
easyocr/character/it_char.txt
easyocr/character/ja_char.txt
easyocr/character/ja_char2.txt
easyocr/character/ja_punc.txt
easyocr/character/kbd_char.txt
easyocr/character/kn.txt
easyocr/character/kn_char.txt
easyocr/character/ko_char.txt
easyocr/character/ku_char.txt
easyocr/character/la_char.txt
easyocr/character/lbe_char.txt
easyocr/character/lez_char.txt
easyocr/character/lt_char.txt
easyocr/character/lv_char.txt
easyocr/character/mah_char.txt
easyocr/character/mai_char.txt
easyocr/character/mi_char.txt
easyocr/character/ml_char.txt
easyocr/character/mn_char.txt
easyocr/character/mr_char.txt
myeasyocr-1.2.3.dist-info/LICENSE
myeasyocr-1.2.3.dist-info/METADATA
myeasyocr-1.2.3.dist-info/WHEEL
myeasyocr-1.2.3.dist-info/entry_points.txt
myeasyocr-1.2.3.dist-info/top_level.txt
myeasyocr-1.2.3.dist-info/RECORD
