Metadata-Version: 2.1
Name: myeasyocr
Version: 1.2.3
Summary: End-to-End Multi-Lingual Optical Character Recognition (OCR) Solution
Home-page: https://github.com/jaidedai/easyocr
Author: Rakpong Kittinaradorn
Author-email: r.kittinaradorn@gmail.com
License: Apache License 2.0
Download-URL: https://github.com/jaidedai/easyocr.git
Keywords: ocr optical character recognition deep learning neural network
Platform: UNKNOWN
Classifier: Development Status :: 5 - Production/Stable
Requires-Dist: torch
Requires-Dist: torchvision (>=0.5)
Requires-Dist: opencv-python
Requires-Dist: scipy
Requires-Dist: numpy
Requires-Dist: Pillow
Requires-Dist: scikit-image
Requires-Dist: python-bidi
Requires-Dist: PyYAML
